README.txt
setup.py
crisp_alpha_vantage/__init__.py
crisp_alpha_vantage/alpha_intelligence.py
crisp_alpha_vantage/commodities.py
crisp_alpha_vantage/economic_indicators.py
crisp_alpha_vantage/exchange_rates.py
crisp_alpha_vantage/fundamental_data.py
crisp_alpha_vantage/series_stock_data.py
crisp_alpha_vantage/settings.py
crisp_alpha_vantage/technical_indicators.py
crisp_alpha_vantage.egg-info/PKG-INFO
crisp_alpha_vantage.egg-info/SOURCES.txt
crisp_alpha_vantage.egg-info/dependency_links.txt
crisp_alpha_vantage.egg-info/top_level.txt