Metadata-Version: 2.1
Name: crisp-alpha-vantage
Version: 1.0.2
Summary: A financial data API, where you can get US stocks, funds, futures, currency exchange rates, economic indicators and other common data.
Author: JiahengLi
Author-email: lijiahengwj@163.com
